KiMoPack_noqt/__init__.py
KiMoPack_noqt/plot_func.py
KiMoPack_noqt-6.13.7.dist-info/LICENSE
KiMoPack_noqt-6.13.7.dist-info/METADATA
KiMoPack_noqt-6.13.7.dist-info/WHEEL
KiMoPack_noqt-6.13.7.dist-info/top_level.txt
KiMoPack_noqt-6.13.7.dist-info/RECORD
