Metadata-Version: 2.1
Name: KiMoPack-noqt
Version: 6.13.7
Summary: A comprehensive package for the analysis of kinetic data.
Home-page: https://github.com/erdzeichen/KiMoPack
Author: Jens Uhlig
Author-email: jens.uhlig@chemphys.lu.se
Project-URL: Bug Tracker, https://github.com/erdzeichen/KiMoPack/issues
Classifier: Programming Language :: Python :: 3
Classifier: License :: OSI Approved :: GNU General Public License v3 (GPLv3)
Classifier: Operating System :: OS Independent
Classifier: Development Status :: 5 - Production/Stable
Classifier: Natural Language :: English
Classifier: Topic :: Scientific/Engineering :: Chemistry
Classifier: Topic :: Scientific/Engineering :: Information Analysis
Classifier: Topic :: Scientific/Engineering :: Physics
Classifier: Framework :: Jupyter
License-File: LICENSE
Requires-Dist: pandas (>="1.1.4")
Requires-Dist: h5py (>="3.1")
Requires-Dist: matplotlib (>="3.3")
Requires-Dist: numpy (>="1.19")
Requires-Dist: lmfit (>="1.0")
Requires-Dist: scipy (>="1.5")
Requires-Dist: pathlib
Requires-Dist: urllib3
Requires-Dist: python-version (>="3.8")
